gitlab_anomaly/__init__.py
gitlab_anomaly/constants.py
gitlab_anomaly/create_test_issues.py
gitlab_anomaly/fetch_gitlab_events.py
gitlab_anomaly/fetch_gitlab_issues.py
gitlab_anomaly/issue_anomaly_detector.py
gitlab_anomaly/main.py
gitlab_anomaly/prepare_pages.py
gitlab_anomaly/test_export_functionality.py
gitlab_anomaly/page_generator/__init__.py
gitlab_anomaly/page_generator/css_generator.py
gitlab_anomaly/page_generator/data_loader.py
gitlab_anomaly/page_generator/js_event_listeners.py
gitlab_anomaly/page_generator/js_rendering.py
gitlab_anomaly/page_generator/js_view_logic.py
gitlab_anomaly/templates/base.html
gitlab_anomaly/templates/content.html
gitlab_issue_anomaly_detector-0.4.0.dist-info/METADATA
gitlab_issue_anomaly_detector-0.4.0.dist-info/WHEEL
gitlab_issue_anomaly_detector-0.4.0.dist-info/entry_points.txt
gitlab_issue_anomaly_detector-0.4.0.dist-info/top_level.txt
gitlab_issue_anomaly_detector-0.4.0.dist-info/RECORD
