Metadata-Version: 2.4
Name: gitlab-issue-anomaly-detector
Version: 0.4.0
Summary: GitLab issue anomaly detection and page generation
Author-email: Author <author@example.com>
License: MIT
Project-URL: Homepage, https://gitlab.com/my-group-name2452611/my-project-name
Project-URL: Bug Tracker, https://gitlab.com/my-group-name2452611/my-project-name/issues
Classifier: Programming Language :: Python :: 3
Classifier: License :: OSI Approved :: MIT License
Classifier: Operating System :: OS Independent
Requires-Python: >=3.6
Requires-Dist: python-dotenv==1.0.0
Requires-Dist: python-gitlab==5.6.0
Requires-Dist: jinja2==3.1.6
